mobilechelonian/__init__.py
mobilechelonian/mobilechelonianjs/paper.js
mobilechelonian/mobilechelonianjs/turtlewidget.js
mobilechelonian-0.5.dist-info/DESCRIPTION.rst
mobilechelonian-0.5.dist-info/METADATA
mobilechelonian-0.5.dist-info/RECORD
mobilechelonian-0.5.dist-info/WHEEL
mobilechelonian-0.5.dist-info/metadata.json
mobilechelonian-0.5.dist-info/top_level.txt
