Metadata-Version: 2.0
Name: mobilechelonian
Version: 0.5
Summary: Turtles in the Jupyter Notebook
Home-page: https://github.com/takluyver/mobilechelonian
Author: Thomas Kluyver
Author-email: thomas@kluyver.me.uk
License: UNKNOWN
Platform: UNKNOWN
Classifier: Framework :: IPython
Classifier: Intended Audience :: Education
Classifier: License :: OSI Approved :: BSD License
Classifier: Programming Language :: Python :: 2
Classifier: Programming Language :: Python :: 3
Classifier: Topic :: Artistic Software
Classifier: Topic :: Education
Requires-Dist: IPython
Requires-Dist: ipywidgets (>=7.0.0)
